<FRAME>
<LEXICALUNIT ID="TUR10-0019950">
<ELEMENT>Agent</ELEMENT>
<ELEMENT>Activity</ELEMENT>
<ELEMENT>Duration</ELEMENT>
</LEXICALUNIT>
<LEXICALUNIT ID="TUR10-0718460">
<ELEMENT>Agent</ELEMENT>
<ELEMENT>Activity</ELEMENT>
<ELEMENT>Duration</ELEMENT>
</LEXICALUNIT>
<LEXICALUNIT ID="TUR10-0915620">
<ELEMENT>Agent</ELEMENT>
<ELEMENT>Activity</ELEMENT>
<ELEMENT>Duration</ELEMENT>
</LEXICALUNIT>
<LEXICALUNIT ID="TUR10-0915630">
<ELEMENT>Agent</ELEMENT>
<ELEMENT>Activity</ELEMENT>
<ELEMENT>Duration</ELEMENT>
</LEXICALUNIT>
<LEXICALUNIT ID="TUR10-0683210">
<ELEMENT>Agent</ELEMENT>
<ELEMENT>Duration</ELEMENT>
</LEXICALUNIT>
<LEXICALUNIT ID="TUR10-1144740">
<ELEMENT>Agent</ELEMENT>
<ELEMENT>Duration</ELEMENT>
</LEXICALUNIT>
<LEXICALUNIT ID="TUR10-0386060">
<ELEMENT>Agent</ELEMENT>
<ELEMENT>Theme</ELEMENT>
<ELEMENT>Duration</ELEMENT>
</LEXICALUNIT>
<LEXICALUNIT ID="TUR10-1144450">
<ELEMENT>Agent</ELEMENT>
<ELEMENT>Duration</ELEMENT>
</LEXICALUNIT>
<LEXICALUNIT ID="TUR10-0804760">
<ELEMENT>Agent</ELEMENT>
<ELEMENT>Duration</ELEMENT>
<ELEMENT>Goal</ELEMENT>
</LEXICALUNIT>
<LEXICALUNIT ID="TUR10-1092870">
<ELEMENT>Agent</ELEMENT>
<ELEMENT>Duration</ELEMENT>
<ELEMENT>Theme</ELEMENT>
</LEXICALUNIT>
<LEXICALUNIT ID="TUR10-1144730">
<ELEMENT>Agent</ELEMENT>
<ELEMENT>Duration</ELEMENT>
<ELEMENT>Theme</ELEMENT>
</LEXICALUNIT>
<LEXICALUNIT ID="TUR10-0019950">
<ELEMENT>Agent</ELEMENT>
<ELEMENT>Duration</ELEMENT>
</LEXICALUNIT>
<LEXICALUNIT ID="TUR10-0718460">
<ELEMENT>Agent</ELEMENT>
<ELEMENT>Duration</ELEMENT>
<ELEMENT>Theme</ELEMENT>
</LEXICALUNIT>
<LEXICALUNIT ID="TUR10-0939420">
<ELEMENT>Agent</ELEMENT>
<ELEMENT>Duration</ELEMENT>
</LEXICALUNIT>
<LEXICALUNIT ID="TUR10-0953430">
<ELEMENT>Agent</ELEMENT>
<ELEMENT>Duration</ELEMENT>
</LEXICALUNIT>
<LEXICALUNIT ID="TUR10-0939440">
<ELEMENT>Agent</ELEMENT>
<ELEMENT>Duration</ELEMENT>
</LEXICALUNIT>
<LEXICALUNIT ID="TUR10-1169880">
<ELEMENT>Agent</ELEMENT>
<ELEMENT>Duration</ELEMENT>
<ELEMENT>Theme</ELEMENT>
</LEXICALUNIT>
<LEXICALUNIT ID="TUR10-0290400">
<ELEMENT>Agent</ELEMENT>
<ELEMENT>Duration</ELEMENT>
</LEXICALUNIT>
<LEXICALUNIT ID="TUR10-0405100">
<ELEMENT>Agent</ELEMENT>
<ELEMENT>Duration</ELEMENT>
</LEXICALUNIT>
<LEXICALUNIT ID="TUR10-1161200">
<ELEMENT>Agent</ELEMENT>
<ELEMENT>Duration</ELEMENT>
<ELEMENT>Circumstances</ELEMENT>
</LEXICALUNIT>
</FRAME>