<FRAME>
<LEXICALUNIT ID="TUR10-0100300">
<ELEMENT>Buyer</ELEMENT>
<ELEMENT>Seller</ELEMENT>
<ELEMENT>Goods</ELEMENT>
<ELEMENT>Money</ELEMENT>
<ELEMENT>Rate</ELEMENT>
</LEXICALUNIT>
<LEXICALUNIT ID="TUR10-0620290">
<ELEMENT>Buyer</ELEMENT>
<ELEMENT>Seller</ELEMENT>
<ELEMENT>Goods</ELEMENT>
<ELEMENT>Money</ELEMENT>
<ELEMENT>Location</ELEMENT>
</LEXICALUNIT>
<LEXICALUNIT ID="TUR10-1118610">
<ELEMENT>Buyer</ELEMENT>
<ELEMENT>Seller</ELEMENT>
<ELEMENT>Goods</ELEMENT>
<ELEMENT>Money</ELEMENT>
</LEXICALUNIT>
<LEXICALUNIT ID="TUR10-1070100">
<ELEMENT>Buyer</ELEMENT>
<ELEMENT>Seller</ELEMENT>
<ELEMENT>Goods</ELEMENT>
<ELEMENT>Money</ELEMENT>
<ELEMENT>Rate</ELEMENT>
</LEXICALUNIT>
<LEXICALUNIT ID="TUR10-0988210">
<ELEMENT>Buyer</ELEMENT>
<ELEMENT>Seller</ELEMENT>
<ELEMENT>Goods</ELEMENT>
<ELEMENT>Money</ELEMENT>
<ELEMENT>Rate</ELEMENT>
</LEXICALUNIT>
<LEXICALUNIT ID="TUR10-1118600">
<ELEMENT>Buyer</ELEMENT>
<ELEMENT>Seller</ELEMENT>
<ELEMENT>Goods</ELEMENT>
<ELEMENT>Money</ELEMENT>
<ELEMENT>Result</ELEMENT>
</LEXICALUNIT>
</FRAME>