<FRAME>
<LEXICALUNIT ID="TUR10-1242660">
<ELEMENT>Agent</ELEMENT>
<ELEMENT>Theme</ELEMENT>
<ELEMENT>Goal</ELEMENT>
</LEXICALUNIT>
<LEXICALUNIT ID="TUR10-1116870">
<ELEMENT>Agent</ELEMENT>
<ELEMENT>Theme</ELEMENT>
<ELEMENT>Goal</ELEMENT>
</LEXICALUNIT>
<LEXICALUNIT ID="TUR10-0327650">
<ELEMENT>Agent</ELEMENT>
<ELEMENT>Theme</ELEMENT>
<ELEMENT>Goal</ELEMENT>
</LEXICALUNIT>
<LEXICALUNIT ID="TUR10-0910400">
<ELEMENT>Agent</ELEMENT>
<ELEMENT>Theme</ELEMENT>
<ELEMENT>Goal</ELEMENT>
</LEXICALUNIT>
<LEXICALUNIT ID="TUR10-1095990">
<ELEMENT>Agent</ELEMENT>
<ELEMENT>Theme</ELEMENT>
<ELEMENT>Goal</ELEMENT>
</LEXICALUNIT>
<LEXICALUNIT ID="TUR10-1116450">
<ELEMENT>Agent</ELEMENT>
<ELEMENT>Theme</ELEMENT>
<ELEMENT>Goal</ELEMENT>
</LEXICALUNIT>
<LEXICALUNIT ID="TUR10-1116980">
<ELEMENT>Agent</ELEMENT>
<ELEMENT>Theme</ELEMENT>
<ELEMENT>Goal</ELEMENT>
</LEXICALUNIT>
<LEXICALUNIT ID="TUR10-1117010">
<ELEMENT>Agent</ELEMENT>
<ELEMENT>Theme</ELEMENT>
<ELEMENT>Goal</ELEMENT>
</LEXICALUNIT>
<LEXICALUNIT ID="TUR10-1116550">
<ELEMENT>Agent</ELEMENT>
<ELEMENT>Theme</ELEMENT>
<ELEMENT>Goal</ELEMENT>
</LEXICALUNIT>
<LEXICALUNIT ID="TUR10-0847760">
<ELEMENT>Agent</ELEMENT>
<ELEMENT>Theme</ELEMENT>
<ELEMENT>Goal</ELEMENT>
</LEXICALUNIT>
<LEXICALUNIT ID="TUR10-0907220">
<ELEMENT>Agent</ELEMENT>
<ELEMENT>Theme</ELEMENT>
<ELEMENT>Goal</ELEMENT>
</LEXICALUNIT>
<LEXICALUNIT ID="TUR10-1167220">
<ELEMENT>Agent</ELEMENT>
<ELEMENT>Theme</ELEMENT>
<ELEMENT>Beneficient</ELEMENT>
</LEXICALUNIT>
<LEXICALUNIT ID="TUR10-0711430">
<ELEMENT>Agent</ELEMENT>
<ELEMENT>Theme</ELEMENT>
<ELEMENT>Goal</ELEMENT>
</LEXICALUNIT>
<LEXICALUNIT ID="TUR10-0705580">
<ELEMENT>Agent</ELEMENT>
<ELEMENT>Theme</ELEMENT>
<ELEMENT>Beneficient</ELEMENT>
</LEXICALUNIT>
<LEXICALUNIT ID="TUR10-0349020">
<ELEMENT>Agent</ELEMENT>
<ELEMENT>Location</ELEMENT>
</LEXICALUNIT>
<LEXICALUNIT ID="TUR10-1117080">
<ELEMENT>Agent</ELEMENT>
<ELEMENT>Theme</ELEMENT>
<ELEMENT>Beneficient</ELEMENT>
</LEXICALUNIT>
<LEXICALUNIT ID="TUR10-1042620">
<ELEMENT>Agent</ELEMENT>
<ELEMENT>Theme</ELEMENT>
</LEXICALUNIT>
<LEXICALUNIT ID="TUR10-1117100">
<ELEMENT>Agent</ELEMENT>
</LEXICALUNIT>
</FRAME>